vision_unlearning/__init__.py
vision_unlearning/datasets/__init__.py
vision_unlearning/datasets/base.py
vision_unlearning/datasets/cifar.py
vision_unlearning/datasets/coco.py
vision_unlearning/datasets/imagenette.py
vision_unlearning/datasets/local.py
vision_unlearning/datasets/others.py
vision_unlearning/evaluator/__init__.py
vision_unlearning/evaluator/class_unlearning.py
vision_unlearning/evaluator/text_to_image.py
vision_unlearning/integrations/__init__.py
vision_unlearning/integrations/huggingface.py
vision_unlearning/integrations/local.py
vision_unlearning/integrations/tensorboard.py
vision_unlearning/integrations/wandb.py
vision_unlearning/metrics/__init__.py
vision_unlearning/metrics/base.py
vision_unlearning/metrics/fid.py
vision_unlearning/metrics/image.py
vision_unlearning/metrics/image_and_image.py
vision_unlearning/metrics/image_and_text.py
vision_unlearning/unlearner/__init__.py
vision_unlearning/unlearner/base.py
vision_unlearning/unlearner/lora.py
vision_unlearning/unlearner/uce_sd_erase.py
vision_unlearning/utils/__init__.py
vision_unlearning/utils/data_generation.py
vision_unlearning/utils/gradient_weighting.py
vision_unlearning/utils/logger.py
vision_unlearning/utils/model_management.py
vision_unlearning/utils/parameter_attribution.py
vision_unlearning/utils/prompts.py
vision_unlearning/utils/training.py
vision_unlearning-0.1.7.dist-info/METADATA
vision_unlearning-0.1.7.dist-info/WHEEL
vision_unlearning-0.1.7.dist-info/licenses/LICENSE
vision_unlearning-0.1.7.dist-info/RECORD
